<Properties StartupConfiguration="{BD6CA4FB-CC92-4331-BF5D-CD7371207CF0}|Default">
  <MonoDevelop.Ide.ItemProperties.Labo2ASPdotNet PreferredExecutionTarget="/Applications/Google Chrome.app" />
  <MonoDevelop.Ide.Workbench ActiveDocument="Labo2ASPdotNet/Models/Entities/Account.cs">
    <Files>
      <File FileName="Labo2ASPdotNet/docker-compose.yaml" Line="9" Column="30" />
      <File FileName="Labo2ASPdotNet/Database/DataContext.cs" Line="17" Column="1" />
      <File FileName="Labo2ASPdotNet/appsettings.json" Line="13" Column="2" />
      <File FileName="Labo2ASPdotNet/Startup.cs" Line="34" Column="10" />
      <File FileName="Labo2ASPdotNet/Program.cs" Line="16" Column="21" />
      <File FileName="Labo2ASPdotNet/appsettings.Development.json" Line="6" Column="24" />
      <File FileName="Labo2ASPdotNet/Migrations/20210430034058_InitialCreate.cs" Line="1" Column="1" />
      <File FileName="Labo2ASPdotNet/Migrations/DataContextModelSnapshot.cs" Line="1" Column="1" />
      <File FileName="Labo2ASPdotNet/README.md" Line="6" Column="1" />
      <File FileName="Labo2ASPdotNet/Migrations/20210430035026_InitialCreate.cs" Line="1" Column="1" />
      <File FileName="Labo2ASPdotNet/Models/Entities/Account.cs" Line="13" Column="6" />
    </Files>
    <Pads>
      <Pad Id="ProjectPad">
        <State name="__root__">
          <Node name="Labo2ASPdotNet" expanded="True">
            <Node name="Labo2ASPdotNet" expanded="True">
              <Node name="Migrations" expanded="True" />
              <Node name="Models" expanded="True">
                <Node name="Entities" expanded="True">
                  <Node name="Account.cs" selected="True" />
                </Node>
              </Node>
            </Node>
          </Node>
        </State>
      </Pad>
    </Pads>
  </MonoDevelop.Ide.Workbench>
  <MonoDevelop.Ide.DebuggingService.PinnedWatches />
  <MonoDevelop.Ide.Workspace ActiveConfiguration="Debug" />
  <MonoDevelop.Ide.DebuggingService.Breakpoints>
    <BreakpointStore />
  </MonoDevelop.Ide.DebuggingService.Breakpoints>
  <MultiItemStartupConfigurations />
</Properties>